onec_webhook/__init__.py
onec_webhook/webhook.py
onec_webhook-0.2.0.dist-info/LICENSE
onec_webhook-0.2.0.dist-info/METADATA
onec_webhook-0.2.0.dist-info/WHEEL
onec_webhook-0.2.0.dist-info/top_level.txt
onec_webhook-0.2.0.dist-info/RECORD
