Metadata-Version: 2.2
Name: onec_webhook
Version: 0.2.0
Summary: Python-библиотека для интеграции с системой взаимодействия 1С
Home-page: https://github.com/Muredsa/onec_webhook
Author: Muresda
Author-email: ads.bagan@yandex.ru
Classifier: Programming Language :: Python :: 3
Classifier: License :: OSI Approved :: MIT License
Classifier: Operating System :: OS Independent
Requires-Python: >=3.7
License-File: LICENSE
Requires-Dist: requests
Dynamic: author
Dynamic: author-email
Dynamic: classifier
Dynamic: description
Dynamic: description-content-type
Dynamic: home-page
Dynamic: requires-dist
Dynamic: requires-python
Dynamic: summary
